f0/conf.py
f0/scripts.py
f0/version.py
f0/f0/init.py
f0-0.1.dist-info/METADATA
f0-0.1.dist-info/WHEEL
f0-0.1.dist-info/entry_points.txt
f0-0.1.dist-info/top_level.txt
f0-0.1.dist-info/RECORD
